jisho/__init__.py
jisho/wiki.py
jisho-0.1.3.dist-info/LICENSE
jisho-0.1.3.dist-info/METADATA
jisho-0.1.3.dist-info/WHEEL
jisho-0.1.3.dist-info/entry_points.txt
jisho-0.1.3.dist-info/top_level.txt
jisho-0.1.3.dist-info/RECORD
