Metadata-Version: 2.1
Name: jisho
Version: 0.1.3
Summary: A wiki generation package for the Sample Programs repo
Home-page: https://github.com/TheRenegadeCoder/sample-programs-wiki
Author: The Renegade Coder
Author-email: jeremy.grifski@therenegadecoder.com
License: UNKNOWN
Platform: UNKNOWN
Classifier: Programming Language :: Python :: 3
Classifier: Operating System :: OS Independent
License-File: LICENSE
Requires-Dist: SnakeMD (>=0.10)
Requires-Dist: subete (>=0.11)
